{
    "menu": [{
            "name": "Dashboards",
            "badge": "2",
            "badgeClass": "badge badge-light-warning badge-pill ml-auto mr-1",
            "icon": "home",
            "url": "dashboard/analytics",
            "slug": "dashboard-analytics",
            "permission": "dashboard"
        },

        {
            "navheader": "Master Data",
            "slug": ""
        },
        {
            "url": "master/jobs",
            "name": "Jobs",
            "icon": "circle-o",
            "slug": "master-jobs",
            "permission": "master-jobs"
        },
        {
            "url": "master/departments",
            "name": "Departments",
            "icon": "circle-o",
            "slug": "master-departments",
            "permission": "master-departments"
        },
        {
            "url": "master/locations",
            "name": "Locations",
            "icon": "circle-o",
            "slug": "master-locations",
            "permission": "master-locations"
        },

        {
            "navheader": "Employee",
            "slug": ""
        },
        {
            "name": "Employee",
            "icon": "user",
            "slug": "",
            "submenu": [{
                    "url": "app/user/list",
                    "name": "List",
                    "icon": "circle",
                    "slug": "app-user-list"
                },
                {
                    "url": "app/user/view",
                    "name": "View",
                    "icon": "circle",
                    "slug": "app-user-view"
                },
                {
                    "url": "app/user/edit",
                    "name": "Edit",
                    "icon": "circle",
                    "slug": "app-user-edit"
                }
            ]
        },

        {
            "navheader": "Work",
            "slug": ""
        },
        {
            "url": "work/task",
            "name": "Tasks",
            "icon": "circle-o",
            "slug": "work-task",
            "permission": "work-task"
        },
        {
            "url": "work/target",
            "name": "Target",
            "icon": "circle-o",
            "slug": "work-target",
            "permission": "work-target",
            "submenu": [{
                    "url": "work/target/daily",
                    "name": "Daily Target",
                    "icon": "circle-o",
                    "slug": "work-target-daily",
                    "permission": "work-target-daily"
                },
                {
                    "url": "work/target/monthly",
                    "name": "Monthly Target",
                    "icon": "circle-o",
                    "slug": "work-target-Monthly",
                    "permission": "work-target-monthly"
                }
            ]
        },
        {
            "url": "work/output",
            "name": "Work Output",
            "icon": "circle-o",
            "slug": "work-output",
            "permission": "work-output"
        },

        {
            "navheader": "Report",
            "slug": ""
        },
        {
            "url": "report",
            "name": "Report",
            "icon": "circle-o",
            "slug": "report",
            "permission": "report"
        },

        {
            "navheader": "Settings",
            "slug": ""
        },
        {
            "url": "settings/company",
            "name": "Company",
            "icon": "circle-o",
            "slug": "settings-company",
            "permission": "settings-company"
        },
        {
            "url": "settings/global",
            "name": "Parameters",
            "icon": "circle-o",
            "slug": "settings-global",
            "permission": "settings-global"
        },
        {
            "url": "settings/theme",
            "name": "Theme",
            "icon": "circle-o",
            "slug": "settings-theme",
            "permission": "settings-theme"
        }

    ]
}